
    {
      "@context": "https://schema.org",
      "@type": "ConvenienceStore",
      "@id": "https://as.chizumaru.com/famima/detailMap?account=famima&bid=22612",
      
        "name": "ファミリーマート 市原姉ヶ崎駅入口店",
      
      "image": [
        "https://as.chizumaru.com/famima/Views/0/Pc/img/logo_fm_sq.png"
       ],
      "address": {
        "@type": "PostalAddress",
        "address": "千葉県市原市姉崎東三丁目 ３番地１８",
        "postalCode": "2990111",
        "addressCountry": "JP"
      },
      "geo": {
        "@type": "GeoCoordinates",
        "latitude": 35.4763475874045,
        "longitude": 140.041143185413
      },
      "url": "https://as.chizumaru.com/famima/detailMap?account=famima&bid=22612",
      "telephone": "0436-60-1031",
      "openingHoursSpecification": [
        {
          "@type": "OpeningHoursSpecification",
          "dayOfWeek": [
            "Monday",
            "Tuesday",
            "Wednesday",
            "Thursday",
            "Friday",
            "Saturday",
            "Sunday"
          ],
          
          
            "opens": "0:00",
            "closes": "23:59"
          
        },
        {
          "description": ""
        }
      ]
    }
    