
    {
      "@context": "https://schema.org",
      "@type": "ConvenienceStore",
      "@id": "https://as.chizumaru.com/famima/detailMap?account=famima&bid=23430",
      
        "name": "ファミリーマート アトレ浦和店",
      
      "image": [
        "https://as.chizumaru.com/famima/Views/0/Pc/img/logo_fm_sq.png"
       ],
      "address": {
        "@type": "PostalAddress",
        "address": "埼玉県さいたま市浦和区高砂一丁目１６番１２号",
        "postalCode": "3300063",
        "addressCountry": "JP"
      },
      "geo": {
        "@type": "GeoCoordinates",
        "latitude": 35.859541883612,
        "longitude": 139.656591477232
      },
      "url": "https://as.chizumaru.com/famima/detailMap?account=famima&bid=23430",
      "telephone": "048-811-2225",
      "openingHoursSpecification": [
        {
          "@type": "OpeningHoursSpecification",
          "dayOfWeek": [
            "Monday",
            "Tuesday",
            "Wednesday",
            "Thursday",
            "Friday",
            "Saturday",
            "Sunday"
          ],
          
          
            "opens": "7:00",
            "closes": "23:00"
          
        },
        {
          "description": ""
        }
      ]
    }
    