
    {
      "@context": "https://schema.org",
      "@type": "ConvenienceStore",
      "@id": "https://as.chizumaru.com/famima/detailMap?account=famima&bid=23438",
      
        "name": "ファミリーマート 柏駅店",
      
      "image": [
        "https://as.chizumaru.com/famima/Views/0/Pc/img/logo_fm_sq.png"
       ],
      "address": {
        "@type": "PostalAddress",
        "address": "千葉県柏市末広町１－１",
        "postalCode": "2770842",
        "addressCountry": "JP"
      },
      "geo": {
        "@type": "GeoCoordinates",
        "latitude": 35.8623990617103,
        "longitude": 139.97053227317
      },
      "url": "https://as.chizumaru.com/famima/detailMap?account=famima&bid=23438",
      "telephone": "04-7142-8188",
      "openingHoursSpecification": [
        {
          "@type": "OpeningHoursSpecification",
          "dayOfWeek": [
            "Monday",
            "Tuesday",
            "Wednesday",
            "Thursday",
            "Friday",
            "Saturday",
            "Sunday"
          ],
          
          
            "opens": "6:00",
            "closes": "23:30"
          
        },
        {
          "description": ""
        }
      ]
    }
    