
    {
      "@context": "https://schema.org",
      "@type": "ConvenienceStore",
      "@id": "https://as.chizumaru.com/famima/detailMap?account=famima&bid=23684",
      
        "name": "ファミリーマート ＪＡ大北あづみ病院店",
      
      "image": [
        "https://as.chizumaru.com/famima/Views/0/Pc/img/logo_fm_sq.png"
       ],
      "address": {
        "@type": "PostalAddress",
        "address": "長野県北安曇郡池田町大字池田 ３２０７番地１",
        "postalCode": "3998695",
        "addressCountry": "JP"
      },
      "geo": {
        "@type": "GeoCoordinates",
        "latitude": 36.4216276095199,
        "longitude": 137.873086713464
      },
      "url": "https://as.chizumaru.com/famima/detailMap?account=famima&bid=23684",
      "telephone": "0261-61-4493",
      "openingHoursSpecification": [
        {
          "@type": "OpeningHoursSpecification",
          "dayOfWeek": [
            "Monday",
            "Tuesday",
            "Wednesday",
            "Thursday",
            "Friday",
            "Saturday",
            "Sunday"
          ],
          
          
            "opens": "7:00",
            "closes": "21:00"
          
        },
        {
          "description": ""
        }
      ]
    }
    