
    {
      "@context": "https://schema.org",
      "@type": "ConvenienceStore",
      "@id": "https://as.chizumaru.com/famima/detailMap?account=famima&bid=25126",
      
        "name": "ファミリーマート 札幌新琴似２条店",
      
      "image": [
        "https://as.chizumaru.com/famima/Views/0/Pc/img/logo_fm_sq.png"
       ],
      "address": {
        "@type": "PostalAddress",
        "address": "北海道札幌市北区新琴似２条 １１丁目１番１０号",
        "postalCode": "0010902",
        "addressCountry": "JP"
      },
      "geo": {
        "@type": "GeoCoordinates",
        "latitude": 43.11151711235,
        "longitude": 141.311374119159
      },
      "url": "https://as.chizumaru.com/famima/detailMap?account=famima&bid=25126",
      "telephone": "011-769-3014",
      "openingHoursSpecification": [
        {
          "@type": "OpeningHoursSpecification",
          "dayOfWeek": [
            "Monday",
            "Tuesday",
            "Wednesday",
            "Thursday",
            "Friday",
            "Saturday",
            "Sunday"
          ],
          
          
            "opens": "0:00",
            "closes": "23:59"
          
        },
        {
          "description": ""
        }
      ]
    }
    