
    {
      "@context": "https://schema.org",
      "@type": "ConvenienceStore",
      "@id": "https://as.chizumaru.com/famima/detailMap?account=famima&bid=26796",
      
        "name": "ファミリーマート リバーゲート箱崎店",
      
      "image": [
        "https://as.chizumaru.com/famima/Views/0/Pc/img/logo_fm_sq.png"
       ],
      "address": {
        "@type": "PostalAddress",
        "address": "東京都中央区日本橋箱崎町 ３６番２号",
        "postalCode": "1030015",
        "addressCountry": "JP"
      },
      "geo": {
        "@type": "GeoCoordinates",
        "latitude": 35.6802613647898,
        "longitude": 139.788564772254
      },
      "url": "https://as.chizumaru.com/famima/detailMap?account=famima&bid=26796",
      "telephone": "03-5847-7051",
      "openingHoursSpecification": [
        {
          "@type": "OpeningHoursSpecification",
          "dayOfWeek": [
            "Monday",
            "Tuesday",
            "Wednesday",
            "Thursday",
            "Friday",
            "Saturday",
            "Sunday"
          ],
          
          
            "opens": "7:00",
            "closes": "23:00"
          
        },
        {
          "description": ""
        }
      ]
    }
    