
    {
      "@context": "https://schema.org",
      "@type": "ConvenienceStore",
      "@id": "https://as.chizumaru.com/famima/detailMap?account=famima&bid=27410",
      
        "name": "ファミリーマート 松本駅東口店",
      
      "image": [
        "https://as.chizumaru.com/famima/Views/0/Pc/img/logo_fm_sq.png"
       ],
      "address": {
        "@type": "PostalAddress",
        "address": "長野県松本市深志一丁目２番３１号",
        "postalCode": "3900815",
        "addressCountry": "JP"
      },
      "geo": {
        "@type": "GeoCoordinates",
        "latitude": 36.2306506623422,
        "longitude": 137.966163777366
      },
      "url": "https://as.chizumaru.com/famima/detailMap?account=famima&bid=27410",
      "telephone": "0263-37-1006",
      "openingHoursSpecification": [
        {
          "@type": "OpeningHoursSpecification",
          "dayOfWeek": [
            "Monday",
            "Tuesday",
            "Wednesday",
            "Thursday",
            "Friday",
            "Saturday",
            "Sunday"
          ],
          
          
            "opens": "0:00",
            "closes": "23:59"
          
        },
        {
          "description": "日曜のみ時短営業（日曜２４：００閉店、月曜６：００開店）"
        }
      ]
    }
    