
    {
      "@context": "https://schema.org",
      "@type": "ConvenienceStore",
      "@id": "https://as.chizumaru.com/famima/detailMap?account=famima&bid=51073",
      
        "name": "トモニー大泉学園駅店",
      
      "image": [
        "https://as.chizumaru.com/famima/Views/0/Pc/img/logo_fm_sq.png"
       ],
      "address": {
        "@type": "PostalAddress",
        "address": "東京都練馬区東大泉１丁目２９－７",
        "postalCode": "1780063",
        "addressCountry": "JP"
      },
      "geo": {
        "@type": "GeoCoordinates",
        "latitude": 35.7495884186383,
        "longitude": 139.586422367712
      },
      "url": "https://as.chizumaru.com/famima/detailMap?account=famima&bid=51073",
      "telephone": "03-5947-3431",
      "openingHoursSpecification": [
        {
          "@type": "OpeningHoursSpecification",
          "dayOfWeek": [
            "Monday",
            "Tuesday",
            "Wednesday",
            "Thursday",
            "Friday",
            "Saturday",
            "Sunday"
          ],
          
          
            "opens": "6:30",
            "closes": "23:00"
          
        },
        {
          "description": ""
        }
      ]
    }
    