
    {
      "@context": "https://schema.org",
      "@type": "ConvenienceStore",
      "@id": "https://as.chizumaru.com/famima/detailMap?account=famima&bid=55578",
      
        "name": "ファミリーマート 近鉄白子駅改札外橋上店",
      
      "image": [
        "https://as.chizumaru.com/famima/Views/0/Pc/img/logo_fm_sq.png"
       ],
      "address": {
        "@type": "PostalAddress",
        "address": "三重県鈴鹿市白子駅前２２－１",
        "postalCode": "5100241",
        "addressCountry": "JP"
      },
      "geo": {
        "@type": "GeoCoordinates",
        "latitude": 34.8342139835136,
        "longitude": 136.589731390194
      },
      "url": "https://as.chizumaru.com/famima/detailMap?account=famima&bid=55578",
      "telephone": "059-380-2301",
      "openingHoursSpecification": [
        {
          "@type": "OpeningHoursSpecification",
          "dayOfWeek": [
            "Monday",
            "Tuesday",
            "Wednesday",
            "Thursday",
            "Friday",
            "Saturday",
            "Sunday"
          ],
          
          
            "opens": "6:00",
            "closes": "22:30"
          
        },
        {
          "description": ""
        }
      ]
    }
    