
    {
      "@context": "https://schema.org",
      "@type": "ConvenienceStore",
      "@id": "https://as.chizumaru.com/famima/detailMap?account=famima&bid=57175",
      
        "name": "ファミリーマート シーバンス ア・モール店",
      
      "image": [
        "https://as.chizumaru.com/famima/Views/0/Pc/img/logo_fm_sq.png"
       ],
      "address": {
        "@type": "PostalAddress",
        "address": "東京都港区芝浦１丁目２－２ シーバンス ア・モール",
        "postalCode": "1050023",
        "addressCountry": "JP"
      },
      "geo": {
        "@type": "GeoCoordinates",
        "latitude": 35.6498050633746,
        "longitude": 139.756559832649
      },
      "url": "https://as.chizumaru.com/famima/detailMap?account=famima&bid=57175",
      "telephone": "03-5427-3188",
      "openingHoursSpecification": [
        {
          "@type": "OpeningHoursSpecification",
          "dayOfWeek": [
            "Monday",
            "Tuesday",
            "Wednesday",
            "Thursday",
            "Friday",
            "Saturday",
            "Sunday"
          ],
          
          
            "opens": "7:00",
            "closes": "22:00"
          
        },
        {
          "description": ""
        }
      ]
    }
    