
    {
      "@context": "https://schema.org",
      "@type": "ConvenienceStore",
      "@id": "https://as.chizumaru.com/famima/detailMap?account=famima&bid=61704",
      
        "name": "ファミリーマート 女川中央店",
      
      "image": [
        "https://as.chizumaru.com/famima/Views/0/Pc/img/logo_fm_sq.png"
       ],
      "address": {
        "@type": "PostalAddress",
        "address": "宮城県牡鹿郡女川町女川二丁目 １５番地の２",
        "postalCode": "9862265",
        "addressCountry": "JP"
      },
      "geo": {
        "@type": "GeoCoordinates",
        "latitude": 38.4444586648683,
        "longitude": 141.446539796636
      },
      "url": "https://as.chizumaru.com/famima/detailMap?account=famima&bid=61704",
      "telephone": "0225-50-1134",
      "openingHoursSpecification": [
        {
          "@type": "OpeningHoursSpecification",
          "dayOfWeek": [
            "Monday",
            "Tuesday",
            "Wednesday",
            "Thursday",
            "Friday",
            "Saturday",
            "Sunday"
          ],
          
          
            "opens": "0:00",
            "closes": "23:59"
          
        },
        {
          "description": ""
        }
      ]
    }
    