
    {
      "@context": "https://schema.org",
      "@type": "ConvenienceStore",
      "@id": "https://as.chizumaru.com/famima/detailMap?account=famima&bid=62130",
      
        "name": "ファミリーマート 鯵ヶ沢バイパス店",
      
      "image": [
        "https://as.chizumaru.com/famima/Views/0/Pc/img/logo_fm_sq.png"
       ],
      "address": {
        "@type": "PostalAddress",
        "address": "青森県西津軽郡鰺ヶ沢町大字舞戸町字下富田９１－１",
        "postalCode": "0382761",
        "addressCountry": "JP"
      },
      "geo": {
        "@type": "GeoCoordinates",
        "latitude": 40.7754019822382,
        "longitude": 140.223487037698
      },
      "url": "https://as.chizumaru.com/famima/detailMap?account=famima&bid=62130",
      "telephone": "0173-82-1211",
      "openingHoursSpecification": [
        {
          "@type": "OpeningHoursSpecification",
          "dayOfWeek": [
            "Monday",
            "Tuesday",
            "Wednesday",
            "Thursday",
            "Friday",
            "Saturday",
            "Sunday"
          ],
          
          
            "opens": "0:00",
            "closes": "23:59"
          
        },
        {
          "description": ""
        }
      ]
    }
    