
    {
      "@context": "https://schema.org",
      "@type": "ConvenienceStore",
      "@id": "https://as.chizumaru.com/famima/detailMap?account=famima&bid=69488",
      
        "name": "ファミリーマート 春日井白山店",
      
      "image": [
        "https://as.chizumaru.com/famima/Views/0/Pc/img/logo_fm_sq.png"
       ],
      "address": {
        "@type": "PostalAddress",
        "address": "愛知県春日井市白山町５丁目 １１番地７",
        "postalCode": "4870034",
        "addressCountry": "JP"
      },
      "geo": {
        "@type": "GeoCoordinates",
        "latitude": 35.271666843797,
        "longitude": 137.027721872201
      },
      "url": "https://as.chizumaru.com/famima/detailMap?account=famima&bid=69488",
      "telephone": "0568-53-4031",
      "openingHoursSpecification": [
        {
          "@type": "OpeningHoursSpecification",
          "dayOfWeek": [
            "Monday",
            "Tuesday",
            "Wednesday",
            "Thursday",
            "Friday",
            "Saturday",
            "Sunday"
          ],
          
          
            "opens": "0:00",
            "closes": "23:59"
          
        },
        {
          "description": ""
        }
      ]
    }
    