
    {
      "@context": "https://schema.org",
      "@type": "ConvenienceStore",
      "@id": "https://as.chizumaru.com/famima/detailMap?account=famima&bid=71023",
      
        "name": "ファミリーマート 小倉徳力五丁目店",
      
      "image": [
        "https://as.chizumaru.com/famima/Views/0/Pc/img/logo_fm_sq.png"
       ],
      "address": {
        "@type": "PostalAddress",
        "address": "福岡県北九州市小倉南区徳力五丁目１番５号",
        "postalCode": "8020974",
        "addressCountry": "JP"
      },
      "geo": {
        "@type": "GeoCoordinates",
        "latitude": 33.8272667000549,
        "longitude": 130.865488150049
      },
      "url": "https://as.chizumaru.com/famima/detailMap?account=famima&bid=71023",
      "telephone": "093-965-0086",
      "openingHoursSpecification": [
        {
          "@type": "OpeningHoursSpecification",
          "dayOfWeek": [
            "Monday",
            "Tuesday",
            "Wednesday",
            "Thursday",
            "Friday",
            "Saturday",
            "Sunday"
          ],
          
          
            "opens": "0:00",
            "closes": "23:59"
          
        },
        {
          "description": ""
        }
      ]
    }
    